uripoint/__init__.py
uripoint/cli.py
uripoint/main.py
uripoint/process.py
uripoint/process_utils.py
uripoint/protocols.py
uripoint/router.py
uripoint-1.9.7.dist-info/LICENSE
uripoint-1.9.7.dist-info/METADATA
uripoint-1.9.7.dist-info/WHEEL
uripoint-1.9.7.dist-info/entry_points.txt
uripoint-1.9.7.dist-info/top_level.txt
uripoint-1.9.7.dist-info/RECORD
