Metadata-Version: 2.1
Name: uripoint
Version: 1.9.7
Summary: A flexible Python library for endpoint management and URI processing
Home-page: https://github.com/uripoint/python
Author: Tom Sapletta
Author-email: info@softreck.dev
Classifier: Development Status :: 4 - Beta
Classifier: Intended Audience :: Developers
Classifier: License :: OSI Approved :: Apache Software License
Classifier: Programming Language :: Python :: 3.7
Classifier: Programming Language :: Python :: 3.8
Classifier: Programming Language :: Python :: 3.9
Classifier: Programming Language :: Python :: 3.10
Requires-Python: >=3.7
License-File: LICENSE
Requires-Dist: pyyaml>=6.0
Requires-Dist: python-dotenv>=0.19.0
Requires-Dist: ffmpeg-python>=0.2.0
Requires-Dist: typing-extensions>=4.0.0
Requires-Dist: colorlog>=6.7.0
Requires-Dist: click>=8.0.0
Requires-Dist: prometheus-client>=0.19.0
Requires-Dist: fastapi>=0.104.1
Requires-Dist: uvicorn>=0.24.0
Requires-Dist: docker>=6.0.0
Requires-Dist: requests>=2.28.0
Provides-Extra: dev
Requires-Dist: pytest>=7.0.0; extra == "dev"
Requires-Dist: pytest-cov>=4.0.0; extra == "dev"
Requires-Dist: black>=23.0.0; extra == "dev"
Requires-Dist: mypy>=1.9.7; extra == "dev"
Requires-Dist: flake8>=6.0.0; extra == "dev"
Requires-Dist: isort>=5.12.0; extra == "dev"
Requires-Dist: coverage>=7.2.0; extra == "dev"
